camoco_cob-0.9.2.data/scripts/cob
camoco_cob-0.9.2.dist-info/DESCRIPTION.rst
camoco_cob-0.9.2.dist-info/METADATA
camoco_cob-0.9.2.dist-info/RECORD
camoco_cob-0.9.2.dist-info/WHEEL
camoco_cob-0.9.2.dist-info/metadata.json
camoco_cob-0.9.2.dist-info/top_level.txt
cob/__init__.py
cob/server.py
cob/cli/cob
cob/static/favicon.ico
cob/static/js/cob.js
cob/static/js/core.js
cob/static/js/enrichment.js
cob/static/js/genes.js
cob/static/js/graph.js
cob/static/js/polywas-layout.js
cob/static/js/tables.js
cob/static/js/tools.js
cob/templates/index.html
