Metadata-Version: 2.0
Name: camoco-cob
Version: 0.9.2
Summary: The Co-Expression Network Browser
Home-page: https://github.com/LinkageIO/cob
Author: Rob Schaefer, Joe Jeffers
Author-email: schae234@gmail.com
License: MIT
Platform: UNKNOWN
Requires-Python: >=3
Requires-Dist: camoco
Requires-Dist: flask (>=0.12)
Requires-Dist: gunicorn (>=19.6.0)
